fileGL/__init__.py
fileGL/fileGL.py
fileGL-1.2.0b1.dist-info/LICENSE
fileGL-1.2.0b1.dist-info/METADATA
fileGL-1.2.0b1.dist-info/WHEEL
fileGL-1.2.0b1.dist-info/top_level.txt
fileGL-1.2.0b1.dist-info/RECORD
