Metadata-Version: 2.1
Name: fileGL
Version: 1.2.0b1
Summary: File organiser with many ways
Home-page: https://github.com/abisheksriram/fileGL
Author: Abishek Sriram
Author-email: abisheksriram2001@gmail.com
License: UNKNOWN
Platform: UNKNOWN
Classifier: Programming Language :: Python :: 3
Classifier: License :: OSI Approved :: Apache Software License
Classifier: Operating System :: Microsoft :: Windows
Classifier: Development Status :: 3 - Alpha
Classifier: Environment :: Console
Requires-Python: >=3.6
